mcp_client_capabilities/__init__.py
mcp_client_capabilities/example.py
mcp_client_capabilities/mcp-clients.json
mcp_client_capabilities/mcp_types.py
mcp_client_capabilities-0.0.12.dist-info/licenses/LICENSE
mcp_client_capabilities-0.0.12.dist-info/METADATA
mcp_client_capabilities-0.0.12.dist-info/WHEEL
mcp_client_capabilities-0.0.12.dist-info/top_level.txt
mcp_client_capabilities-0.0.12.dist-info/RECORD
