Metadata-Version: 2.4
Name: mcp-client-capabilities
Version: 0.0.12
Summary: Index of all Model Context Protocol (MCP) clients and their capabilities
Author: Apify
License-Expression: Apache-2.0
Requires-Python: >=3.12
License-File: LICENSE
Dynamic: license-file
